qchviewer/__init__.py
qchviewer/__main__.py
qchviewer/qchviewer.py
qchviewer-0.1.3.dist-info/DESCRIPTION.rst
qchviewer-0.1.3.dist-info/METADATA
qchviewer-0.1.3.dist-info/RECORD
qchviewer-0.1.3.dist-info/WHEEL
qchviewer-0.1.3.dist-info/entry_points.txt
qchviewer-0.1.3.dist-info/metadata.json
qchviewer-0.1.3.dist-info/top_level.txt
tests/__init__.py
tests/test_qchviewer.py
