Metadata-Version: 2.0
Name: qchviewer
Version: 0.1.3
Summary: A simple script to directly open standalone Qt Help file by Assistant
Home-page: https://github.com/starofrainnight/qchviewer
Author: Hong-She Liang
Author-email: starofrainnight@gmail.com
License: Apache Software License
Keywords: qchviewer
Platform: UNKNOWN
Classifier: Development Status :: 2 - Pre-Alpha
Classifier: Intended Audience :: Developers
Classifier: License :: OSI Approved :: Apache Software License
Classifier: Natural Language :: English
Classifier: Programming Language :: Python :: 3
Classifier: Programming Language :: Python :: 3.4
Classifier: Programming Language :: Python :: 3.5
Requires-Dist: click (>=6.0)
Requires-Dist: jinja2
